sin-cos/original/CORDIC.v
`timescale 1 ns/100 ps

//------------------------------------------------------------------------------
//          Copyright (c) 2012 Kirk Weedman, KD7IRS, kirk@hdlexpress.com
//------------------------------------------------------------------------------

// NOTE: 1. Input angle is a modulo of 2*PI scaled to fit in a 32bit register. The user must translate
//          this angle to a value from 0 - (2^32-1).  0 deg = 32'h0, 359.9999... = 32'hFF_FF_FF_FF
//          To translate from degrees to a 32 bit value, multiply 2^32 by the angle (in degrees),
//          then divide by 360
//       2. Size of Xout, Yout is 1 bit larger due to a system gain of 1.647 (which is < 2)
module CORDIC (clock, angle, Xin, Yin, Xout, Yout);
   
   parameter XY_SZ = 16;   // width of input and output data
   
   localparam STG = XY_SZ; // same as bit width of X and Y
   
   input                      clock;
   // angle is a signed value in the range of -PI to +PI that must be represented as a 32 bit signed number
   input  signed       [31:0] angle;
   input  signed  [XY_SZ-1:0] Xin;
   input  signed  [XY_SZ-1:0] Yin;
   output signed    [XY_SZ:0] Xout;
   output signed    [XY_SZ:0] Yout;
   
   //------------------------------------------------------------------------------
   //                             arctan table
   //------------------------------------------------------------------------------
   
   // Note: The atan_table was chosen to be 31 bits wide giving resolution up to atan(2^-30)
   wire signed [31:0] atan_table [0:30];
   
   // upper 2 bits = 2'b00 which represents 0 - PI/2 range
   // upper 2 bits = 2'b01 which represents PI/2 to PI range
   // upper 2 bits = 2'b10 which represents PI to 3*PI/2 range (i.e. -PI/2 to -PI)
   // upper 2 bits = 2'b11 which represents 3*PI/2 to 2*PI range (i.e. 0 to -PI/2)
   // The upper 2 bits therefore tell us which quadrant we are in.
   assign atan_table[00] = 32'b00100000000000000000000000000000; // 45.000 degrees -> atan(2^0)
   assign atan_table[01] = 32'b00010010111001000000010100011101; // 26.565 degrees -> atan(2^-1)
   assign atan_table[02] = 32'b00001001111110110011100001011011; // 14.036 degrees -> atan(2^-2)
   assign atan_table[03] = 32'b00000101000100010001000111010100; // atan(2^-3)
   assign atan_table[04] = 32'b00000010100010110000110101000011;
   assign atan_table[05] = 32'b00000001010001011101011111100001;
   assign atan_table[06] = 32'b00000000101000101111011000011110;
   assign atan_table[07] = 32'b00000000010100010111110001010101;
   assign atan_table[08] = 32'b00000000001010001011111001010011;
   assign atan_table[09] = 32'b00000000000101000101111100101110;
   assign atan_table[10] = 32'b00000000000010100010111110011000;
   assign atan_table[11] = 32'b00000000000001010001011111001100;
   assign atan_table[12] = 32'b00000000000000101000101111100110;
   assign atan_table[13] = 32'b00000000000000010100010111110011;
   assign atan_table[14] = 32'b00000000000000001010001011111001;
   assign atan_table[15] = 32'b00000000000000000101000101111101;
   assign atan_table[16] = 32'b00000000000000000010100010111110;
   assign atan_table[17] = 32'b00000000000000000001010001011111;
   assign atan_table[18] = 32'b00000000000000000000101000101111;
   assign atan_table[19] = 32'b00000000000000000000010100011000;
   assign atan_table[20] = 32'b00000000000000000000001010001100;
   assign atan_table[21] = 32'b00000000000000000000000101000110;
   assign atan_table[22] = 32'b00000000000000000000000010100011;
   assign atan_table[23] = 32'b00000000000000000000000001010001;
   assign atan_table[24] = 32'b00000000000000000000000000101000;
   assign atan_table[25] = 32'b00000000000000000000000000010100;
   assign atan_table[26] = 32'b00000000000000000000000000001010;
   assign atan_table[27] = 32'b00000000000000000000000000000101;
   assign atan_table[28] = 32'b00000000000000000000000000000010;
   assign atan_table[29] = 32'b00000000000000000000000000000001; // atan(2^-29)
   assign atan_table[30] = 32'b00000000000000000000000000000000;
   
   //------------------------------------------------------------------------------
   //                              registers
   //------------------------------------------------------------------------------
   
   //stage outputs
   reg signed [XY_SZ:0] X [0:STG-1];
   reg signed [XY_SZ:0] Y [0:STG-1];
   reg signed    [31:0] Z [0:STG-1]; // 32bit
   
   //------------------------------------------------------------------------------
   //                               stage 0
   //------------------------------------------------------------------------------
   wire                 [1:0] quadrant;
   assign   quadrant = angle[31:30];
   
   always @(posedge clock)
   begin // make sure the rotation angle is in the -pi/2 to pi/2 range.  If not then pre-rotate
      case (quadrant)
         2'b00,
         2'b11:   // no pre-rotation needed for these quadrants
         begin    // X[n], Y[n] is 1 bit larger than Xin, Yin, but Verilog handles the assignments properly
            X[0] <= Xin;
            Y[0] <= Yin;
            Z[0] <= angle;
         end
         
         2'b01:
         begin
            X[0] <= -Yin;
            Y[0] <= Xin;
            Z[0] <= {2'b00,angle[29:0]}; // subtract pi/2 from angle for this quadrant
         end
         
         2'b10:
         begin
            X[0] <= Yin;
            Y[0] <= -Xin;
            Z[0] <= {2'b11,angle[29:0]}; // add pi/2 to angle for this quadrant
         end
         
      endcase
   end
   
   //------------------------------------------------------------------------------
   //                           generate stages 1 to STG-1
   //------------------------------------------------------------------------------
   genvar i;

   generate
   for (i=0; i < (STG-1); i=i+1)
   begin: XYZ
      wire                   Z_sign;
      wire signed  [XY_SZ:0] X_shr, Y_shr; 
   
      assign X_shr = X[i] >>> i; // signed shift right
      assign Y_shr = Y[i] >>> i;
   
      //the sign of the current rotation angle
      assign Z_sign = Z[i][31]; // Z_sign = 1 if Z[i] < 0
   
      always @(posedge clock)
      begin
         // add/subtract shifted data
         X[i+1] <= Z_sign ? X[i] + Y_shr         : X[i] - Y_shr;
         Y[i+1] <= Z_sign ? Y[i] - X_shr         : Y[i] + X_shr;
         Z[i+1] <= Z_sign ? Z[i] + atan_table[i] : Z[i] - atan_table[i];
      end
   end
   endgenerate
   
   
   //------------------------------------------------------------------------------
   //                                 output
   //------------------------------------------------------------------------------
   assign Xout = X[STG-1];
   assign Yout = Y[STG-1];

endmodule

original/cordic_test.v
`timescale 1 ns/100 ps

module cordic_test;

localparam  SZ = 16; // bits of accuracy

reg  [SZ-1:0] Xin, Yin;
reg  [31:0] angle;
wire [SZ:0] Xout, Yout;
reg         CLK_100MHZ;
//
// Waveform generator
//
localparam FALSE = 1'b0;
localparam TRUE = 1'b1;

localparam VALUE = 32000/1.647; // reduce by a factor of 1.647 since thats the gain of the system

reg signed [63:0] i;
reg      start;

initial
begin
   $dumpfile("cordic.vcd");
   $dumpvars(0,cordic_test);
   start = FALSE;
   $write("Starting sim");
   CLK_100MHZ = 1'b0;
   angle = 0;
   Xin = VALUE;                     // Xout = 32000*cos(angle)
   Yin = 1'd0;                      // Yout = 32000*sin(angle)

   #1000;
   @(posedge CLK_100MHZ);
   start = TRUE;

   // sin/cos output
   for (i = 0; i < 360; i = i + 1)     // from 0 to 359 degrees in 1 degree increments
//   for (i = 30; i < 60; i = i + 30)     // increment by 30 degrees only
   begin
      @(posedge CLK_100MHZ);
      start = FALSE;
      angle = ((1 << 32)*i)/360;    // example: 45 deg = 45/360 * 2^32 = 32'b00100000000000000000000000000000 = 45.000 degrees -> atan(2^0)
      $display ("angle = %d, %h",i, angle);
   end

   #500
   $write("Simulation has finished");
   $finish;
   $stop;
end

CORDIC sin_cos (CLK_100MHZ, angle, Xin, Yin, Xout, Yout);

parameter CLK100_SPEED = 10;  // 100Mhz = 10nS

initial
begin
  CLK_100MHZ = 1'b0;
  $display ("CLK_100MHZ started");
  #5;
  forever
  begin
    #(CLK100_SPEED/2) CLK_100MHZ = 1'b1;
    #(CLK100_SPEED/2) CLK_100MHZ = 1'b0;
  end
end

endmodule

original/cordic.vcd
$date
	Sun Jan 15 21:54:46 2023
$end
$version
	Icarus Verilog
$end
$timescale
	100ps
$end
$scope module cordic_test $end
$var wire 17 ! Yout [16:0] $end
$var wire 17 " Xout [16:0] $end
$var reg 1 # CLK_100MHZ $end
$var reg 16 $ Xin [15:0] $end
$var reg 16 % Yin [15:0] $end
$var reg 32 & angle [31:0] $end
$var reg 64 ' i [63:0] $end
$var reg 1 ( start $end
$scope module sin_cos $end
$var wire 16 ) Xin [15:0] $end
$var wire 17 * Xout [16:0] $end
$var wire 16 + Yin [15:0] $end
$var wire 17 , Yout [16:0] $end
$var wire 32 - angle [31:0] $end
$var wire 1 # clock $end
$var wire 2 . quadrant [1:0] $end
$scope begin XYZ[0] $end
$var wire 17 / X_shr [16:0] $end
$var wire 17 0 Y_shr [16:0] $end
$var wire 1 1 Z_sign $end
$upscope $end
$scope begin XYZ[1] $end
$var wire 1 2 Z_sign $end
$var wire 17 3 Y_shr [16:0] $end
$var wire 17 4 X_shr [16:0] $end
$upscope $end
$scope begin XYZ[2] $end
$var wire 1 5 Z_sign $end
$var wire 17 6 Y_shr [16:0] $end
$var wire 17 7 X_shr [16:0] $end
$upscope $end
$scope begin XYZ[3] $end
$var wire 1 8 Z_sign $end
$var wire 17 9 Y_shr [16:0] $end
$var wire 17 : X_shr [16:0] $end
$upscope $end
$scope begin XYZ[4] $end
$var wire 1 ; Z_sign $end
$var wire 17 < Y_shr [16:0] $end
$var wire 17 = X_shr [16:0] $end
$upscope $end
$scope begin XYZ[5] $end
$var wire 1 > Z_sign $end
$var wire 17 ? Y_shr [16:0] $end
$var wire 17 @ X_shr [16:0] $end
$upscope $end
$scope begin XYZ[6] $end
$var wire 1 A Z_sign $end
$var wire 17 B Y_shr [16:0] $end
$var wire 17 C X_shr [16:0] $end
$upscope $end
$scope begin XYZ[7] $end
$var wire 1 D Z_sign $end
$var wire 17 E Y_shr [16:0] $end
$var wire 17 F X_shr [16:0] $end
$upscope $end
$scope begin XYZ[8] $end
$var wire 1 G Z_sign $end
$var wire 17 H Y_shr [16:0] $end
$var wire 17 I X_shr [16:0] $end
$upscope $end
$scope begin XYZ[9] $end
$var wire 1 J Z_sign $end
$var wire 17 K Y_shr [16:0] $end
$var wire 17 L X_shr [16:0] $end
$upscope $end
$scope begin XYZ[10] $end
$var wire 1 M Z_sign $end
$var wire 17 N Y_shr [16:0] $end
$var wire 17 O X_shr [16:0] $end
$upscope $end
$scope begin XYZ[11] $end
$var wire 1 P Z_sign $end
$var wire 17 Q Y_shr [16:0] $end
$var wire 17 R X_shr [16:0] $end
$upscope $end
$scope begin XYZ[12] $end
$var wire 1 S Z_sign $end
$var wire 17 T Y_shr [16:0] $end
$var wire 17 U X_shr [16:0] $end
$upscope $end
$scope begin XYZ[13] $end
$var wire 1 V Z_sign $end
$var wire 17 W Y_shr [16:0] $end
$var wire 17 X X_shr [16:0] $end
$upscope $end
$scope begin XYZ[14] $end
$var wire 1 Y Z_sign $end
$var wire 17 Z Y_shr [16:0] $end
$var wire 17 [ X_shr [16:0] $end
$upscope $end
$upscope $end
$upscope $end
$enddefinitions $end
#0
$dumpvars
bx [
bx Z
xY
bx X
bx W
xV
bx U
bx T
xS
bx R
bx Q
xP
bx O
bx N
xM
bx L
bx K
xJ
bx I
bx H
xG
bx F
bx E
xD
bx C
bx B
xA
bx @
bx ?
x>
bx =
bx <
x;
bx :
bx 9
x8
bx 7
bx 6
x5
bx 4
bx 3
x2
x1
bx 0
bx /
b0 .
b0 -
bx ,
b0 +
bx *
b100101111100101 )
0(
bx '
b0 &
b0 %
b100101111100101 $
0#
bx "
bx !
$end
#100
01
b0 0
b100101111100101 /
1#
#150
0#
#200
12
b10010111110010 3
b10010111110010 4
1#
#250
0#
#300
15
b100101111100 6
b1110001110101 7
1#
#350
0#
#400
18
b100101111 9
b111101101010 :
1#
#450
0#
#500
0;
b11111111110100001 <
b11111001000 =
1#
#550
0#
#600
1>
b1110 ?
b1111100111 @
1#
#650
0#
#700
0A
b11111111111110111 B
b111110011 C
1#
#750
0#
#800
0D
b11111111111111111 E
b11111001 F
1#
#850
0#
#900
1G
b0 H
b1111100 I
1#
#950
0#
#1000
1J
b0 K
b111110 L
1#
#1050
0#
#1100
1M
b0 N
b11111 O
1#
#1150
0#
#1200
1P
b0 Q
b1111 R
1#
#1250
0#
#1300
0S
b11111111111111111 T
b111 U
1#
#1350
0#
#1400
0V
b0 W
b11 X
1#
#1450
0#
#1500
1Y
b0 Z
b1 [
1#
#1550
0#
#1600
b10 !
b10 ,
b111110011111010 "
b111110011111010 *
1#
