sin-cos/my_version/cordic.v
module cordic (
    clock,
    angle,
    Xin,
    Yin,
    Xout,
    Yout
);

    parameter size = 16 ;

    localparam stage = size ;

    input clock ;
    input signed [31:0] angle ;
    input signed [size-1:0] Xin ;
    input signed [size-1:0] Yin ;
    output signed [size:0] Xout ;
    output signed [size:0] Yout ;

    wire signed [31:0] atan_table [0:30] ;
    // arctan table
    // values in the table is represented in a 32 bit format
    // atan(2^0) = 45 deg = 45/360 * 2^32
    // atan(2^1) = 26.565 deg = 26.565/360 * 2^32
    assign atan_table[0] = 32'b00100000000000000000000000000000 ;
    assign atan_table[1] = 32'b00010010111001000000010100011101 ;
    assign atan_table[2] = 32'b00001001111110110011100001011011 ;
    assign atan_table[3] = 32'b00000101000100010001000111010100 ;
    assign atan_table[4] = 32'b00000010100010110000110101000011 ;
    assign atan_table[5] = 32'b00000001010001011101011111100001 ;
    assign atan_table[6] = 32'b00000000101000101111011000011110 ;
    assign atan_table[7] = 32'b00000000010100010111110001010101 ;
    assign atan_table[8] = 32'b00000000001010001011111001010011 ;
    assign atan_table[9] = 32'b00000000000101000101111100101110 ;
    assign atan_table[10] = 32'b00000000000010100010111110011000 ;
    assign atan_table[11] = 32'b00000000000001010001011111001100 ;
    assign atan_table[12] = 32'b00000000000000101000101111100110 ;
    assign atan_table[13] = 32'b00000000000000010100010111110011 ;
    assign atan_table[14] = 32'b00000000000000001010001011111001 ;
    assign atan_table[15] = 32'b00000000000000000101000101111100 ;
    assign atan_table[16] = 32'b00000000000000000010100010111110 ;
    assign atan_table[17] = 32'b00000000000000000001010001011111 ;
    assign atan_table[18] = 32'b00000000000000000000101000101111 ;
    assign atan_table[19] = 32'b00000000000000000000010100010111 ;
    assign atan_table[20] = 32'b00000000000000000000001010001011 ;
    assign atan_table[21] = 32'b00000000000000000000000101000101 ;
    assign atan_table[22] = 32'b00000000000000000000000010100010 ;
    assign atan_table[23] = 32'b00000000000000000000000001010001 ;
    assign atan_table[24] = 32'b00000000000000000000000000101000 ;
    assign atan_table[25] = 32'b00000000000000000000000000010100 ;
    assign atan_table[26] = 32'b00000000000000000000000000001010 ;
    assign atan_table[27] = 32'b00000000000000000000000000000101 ;
    assign atan_table[28] = 32'b00000000000000000000000000000010 ;
    assign atan_table[29] = 32'b00000000000000000000000000000001 ;
    assign atan_table[30] = 32'b00000000000000000000000000000000 ;


    reg signed [size:0] X [0:stage-1] ;
    reg signed [size:0] Y [0:stage-1] ;
    reg signed [31:0] Z [0:stage-1] ;



    // Stage 0 

    wire [1:0] quadrant ;

    assign quadrant = angle[31:30] ;

    always @(posedge clock) 
    begin
        case (quadrant)
            2'b00,
            2'b11:
            begin
                X[0] <= Xin ;
                Y[0] <= Yin ;
                Z[0] <= angle ;
            end 

            2'b01:
            begin
                X[0] <= -Yin ;
                Y[0] <= Xin ;
                Z[0] <= {2'b00,angle[29:0]};
            end

            2'b10:
            begin
                X[0] <= Yin ;
                Y[0] <= -Xin ;
                Z[0] <= {2'b11,angle[29:0]};
            end
        endcase
    end

    // Stages 1 to stage - 1

    genvar i ;
    generate
        for (i = 0 ; i < (stage - 1) ; i = i + 1) 
        begin: XYZ
            wire                 Z_sign ;
            wire signed [size:0] X_shr, Y_shr ;

            assign X_shr = X[i] >>> i ;
            assign Y_shr = Y[i] >>> i ;

            assign Z_sign = Z[i][31] ; 

            always @(posedge clock) 
            begin
                X[i+1] <= Z_sign ? X[i] + Y_shr  : X[i] - Y_shr ;
                Y[i+1] <= Z_sign ? Y[i] - X_shr  : Y[i] + X_shr ;
                Z[i+1] <= Z_sign ? Z[i] + atan_table[i]  : Z[i] - atan_table[i] ;    
            end
        end
    endgenerate

    // Output

    assign Xout = X[stage - 1] ;
    assign Yout = Y[stage - 1] ;

endmodule

my_version/cordic_tb.v
`timescale 1 ns/100 ps

module cordic_test ;

localparam sz = 16 ;

reg [sz-1:0] Xin, Yin;
reg [31:0] angle ;
wire [sz:0] Xout, Yout ;

reg clk_100mhz ;

localparam false = 1'b0 ;
localparam true = 1'b1 ;

localparam value = 32000 / 1.647;

reg signed [63:0] i ;
reg start ;

initial 
begin
    $dumpfile("cordic.vcd");
    $dumpvars(0,cordic_test);
    start = false ;
    clk_100mhz = 1'b0 ;
    angle = 0 ;
    Xin = value ;
    Yin = 1'd0 ;

    #1000;
    @(posedge clk_100mhz) ;
    start = true ;

    for (i = 0; i < 360; i = i+1) 
    begin
        @(posedge clk_100mhz) ;
        start = false ;
        angle = ((i << 32)*i)/360 ;    
    end

    #500
    $finish ;
    $stop ;
end

cordic sin_cos (clk_100mhz, angle, Xin, Yin, Xout, Yout) ;

parameter clk_100_speed = 10 ;

initial 
begin
    clk_100mhz = 1'b0 ; 
    #5 ;
    forever begin
        #(clk_100_speed/2) clk_100mhz = 1'b1 ;
        #(clk_100_speed/2) clk_100mhz = 1'b0 ;
    end    
end

endmodule

my_version/cordic.vcd
$date
	Sun Jan 15 22:11:16 2023
$end
$version
	Icarus Verilog
$end
$timescale
	100ps
$end
$scope module cordic_test $end
$var wire 17 ! Yout [16:0] $end
$var wire 17 " Xout [16:0] $end
$var reg 16 # Xin [15:0] $end
$var reg 16 $ Yin [15:0] $end
$var reg 32 % angle [31:0] $end
$var reg 1 & clk_100mhz $end
$var reg 64 ' i [63:0] $end
$var reg 1 ( start $end
$scope module sin_cos $end
$var wire 16 ) Xin [15:0] $end
$var wire 17 * Xout [16:0] $end
$var wire 16 + Yin [15:0] $end
$var wire 17 , Yout [16:0] $end
$var wire 32 - angle [31:0] $end
$var wire 1 & clock $end
$var wire 2 . quadrant [1:0] $end
$scope begin XYZ[0] $end
$var wire 17 / X_shr [16:0] $end
$var wire 17 0 Y_shr [16:0] $end
$var wire 1 1 Z_sign $end
$upscope $end
$scope begin XYZ[1] $end
$var wire 1 2 Z_sign $end
$var wire 17 3 Y_shr [16:0] $end
$var wire 17 4 X_shr [16:0] $end
$upscope $end
$scope begin XYZ[2] $end
$var wire 1 5 Z_sign $end
$var wire 17 6 Y_shr [16:0] $end
$var wire 17 7 X_shr [16:0] $end
$upscope $end
$scope begin XYZ[3] $end
$var wire 1 8 Z_sign $end
$var wire 17 9 Y_shr [16:0] $end
$var wire 17 : X_shr [16:0] $end
$upscope $end
$scope begin XYZ[4] $end
$var wire 1 ; Z_sign $end
$var wire 17 < Y_shr [16:0] $end
$var wire 17 = X_shr [16:0] $end
$upscope $end
$scope begin XYZ[5] $end
$var wire 1 > Z_sign $end
$var wire 17 ? Y_shr [16:0] $end
$var wire 17 @ X_shr [16:0] $end
$upscope $end
$scope begin XYZ[6] $end
$var wire 1 A Z_sign $end
$var wire 17 B Y_shr [16:0] $end
$var wire 17 C X_shr [16:0] $end
$upscope $end
$scope begin XYZ[7] $end
$var wire 1 D Z_sign $end
$var wire 17 E Y_shr [16:0] $end
$var wire 17 F X_shr [16:0] $end
$upscope $end
$scope begin XYZ[8] $end
$var wire 1 G Z_sign $end
$var wire 17 H Y_shr [16:0] $end
$var wire 17 I X_shr [16:0] $end
$upscope $end
$scope begin XYZ[9] $end
$var wire 1 J Z_sign $end
$var wire 17 K Y_shr [16:0] $end
$var wire 17 L X_shr [16:0] $end
$upscope $end
$scope begin XYZ[10] $end
$var wire 1 M Z_sign $end
$var wire 17 N Y_shr [16:0] $end
$var wire 17 O X_shr [16:0] $end
$upscope $end
$scope begin XYZ[11] $end
$var wire 1 P Z_sign $end
$var wire 17 Q Y_shr [16:0] $end
$var wire 17 R X_shr [16:0] $end
$upscope $end
$scope begin XYZ[12] $end
$var wire 1 S Z_sign $end
$var wire 17 T Y_shr [16:0] $end
$var wire 17 U X_shr [16:0] $end
$upscope $end
$scope begin XYZ[13] $end
$var wire 1 V Z_sign $end
$var wire 17 W Y_shr [16:0] $end
$var wire 17 X X_shr [16:0] $end
$upscope $end
$scope begin XYZ[14] $end
$var wire 1 Y Z_sign $end
$var wire 17 Z Y_shr [16:0] $end
$var wire 17 [ X_shr [16:0] $end
$upscope $end
$upscope $end
$upscope $end
$enddefinitions $end
#0
$dumpvars
bx [
bx Z
xY
bx X
bx W
xV
bx U
bx T
xS
bx R
bx Q
xP
bx O
bx N
xM
bx L
bx K
xJ
bx I
bx H
xG
bx F
bx E
xD
bx C
bx B
xA
bx @
bx ?
x>
bx =
bx <
x;
bx :
bx 9
x8
bx 7
bx 6
x5
bx 4
bx 3
x2
x1
bx 0
bx /
b0 .
b0 -
bx ,
b0 +
bx *
b100101111100101 )
0(
bx '
0&
b0 %
b0 $
b100101111100101 #
bx "
bx !
$end
#100
01
b0 0
b100101111100101 /
1&
#150
0&
#200
12
b10010111110010 3
b10010111110010 4
1&
#250
0&
#300
15
b100101111100 6
b1110001110101 7
1&
#350
0&
#400
18
b100101111 9
b111101101010 :
1&
#450
0&
#500
0;
b11111111110100001 <
b11111001000 =
1&
#550
0&
#600
1>
b1110 ?
b1111100111 @
1&
#650
0&
#700
0A
b11111111111110111 B
b111110011 C
1&
#750
0&
#800
0D
b11111111111111111 E
b11111001 F
1&
#850
0&
#900
1G
b0 H
b1111100 I
1&
#950
0&
#1000
1J
b0 K
b111110 L
1&
#1050
0&
#1100
1M
b0 N
b11111 O
1&
#1150
0&
#1200
1P
b0 Q
b1111 R
1&
#1250
0&
#1300
0S
b11111111111111111 T
b111 U
1&
#1350
0&
#1400
0V
b0 W
b11 X
1&
#1450
0&
#1500
1Y
b0 Z
b1 [
1&
#1550
0&
#1600
b10 !
b10 ,
b111110011111010 "
b111110011111010 *
1&
